grafs/__init__.py
grafs/main.py
funcion_graficas-1.2.0.dist-info/LICENSE
funcion_graficas-1.2.0.dist-info/METADATA
funcion_graficas-1.2.0.dist-info/WHEEL
funcion_graficas-1.2.0.dist-info/top_level.txt
funcion_graficas-1.2.0.dist-info/RECORD
