Metadata-Version: 2.1
Name: funcion-graficas
Version: 1.2.0
Summary: Una pequeña librería para crear gráficos de forma sencilla con los estudiantes, de Mateo Dutra
Home-page: https://github.com/J-create-bit/Grafs
Author: Mateo Dutra / Joaquín Ferreiro
Author-email: 
Classifier: Programming Language :: Python :: 3
Classifier: License :: OSI Approved :: MIT License
Classifier: Operating System :: OS Independent
License-File: LICENSE
Requires-Dist: mpi4py >=2.0
Requires-Dist: numpy
Requires-Dist: matplotlib
